README.rst
setup.py
neleval/__init__.py
neleval/__main__.py
neleval/analyze.py
neleval/annotation.py
neleval/brat.py
neleval/configs.py
neleval/coref_metrics.py
neleval/document.py
neleval/evaluate.py
neleval/import_.py
neleval/interact.py
neleval/munkres.py
neleval/prepare.py
neleval/significance.py
neleval/summary.py
neleval/tac.py
neleval/test.py
neleval/utils.py
neleval/weak.py
neleval.egg-info/PKG-INFO
neleval.egg-info/SOURCES.txt
neleval.egg-info/dependency_links.txt
neleval.egg-info/entry_points.txt
neleval.egg-info/pbr.json
neleval.egg-info/requires.txt
neleval.egg-info/top_level.txt