Metadata-Version: 2.1
Name: neleval
Version: 3.1.1
Summary: Command-line evaluation tools for named entity linking and (cross-document) coreference resolution
Home-page: https://github.com/wikilinks/neleval
Author: Joel Nothman, Ben Hachey, Will Radford
Author-email: joel.nothman+neleval@gmail.com
License: Apache 2.0
Download-URL: https://github.com/wikilinks/neleval/tree/v3.1.1
Keywords: clustering,coreference,evaluation,entity disambiguation
Platform: UNKNOWN
Classifier: Intended Audience :: Science/Research
Classifier: License :: OSI Approved :: Apache Software License
Classifier: Programming Language :: Python :: 2.7
Classifier: Programming Language :: Python :: 3
Classifier: Programming Language :: Python :: 3.4
Classifier: Programming Language :: Python :: 3.5
Classifier: Programming Language :: Python :: 3.6
Classifier: Topic :: Scientific/Engineering
Provides-Extra: significance
Provides-Extra: ceaf
Provides-Extra: plots
Provides-Extra: dev
